alithia/__init__.py
alithia/config_loader.py
alithia/constants.py
alithia/models/__init__.py
alithia/models/arxiv_paper.py
alithia/paperlens/__init__.py
alithia/paperlens/engine.py
alithia/paperlens/models.py
alithia/paperlens/paper_ocr/base.py
alithia/paperlens/paper_ocr/docling.py
alithia/paperscout/agent.py
alithia/paperscout/email.py
alithia/paperscout/models.py
alithia/paperscout/nodes.py
alithia/paperscout/reranker.py
alithia/paperscout/state.py
alithia/researcher/__init__.py
alithia/researcher/connection.py
alithia/researcher/profile.py
alithia/researcher/service.py
alithia/run/__main__.py
alithia/storage/__init__.py
alithia/storage/base.py
alithia/storage/factory.py
alithia/storage/sqlite.py
alithia/storage/supabase.py
alithia/utils/arxiv_paper_fetcher.py
alithia/utils/arxiv_paper_utils.py
alithia/utils/arxiv_web_scraper.py
alithia/utils/email_utils.py
alithia/utils/llm_utils.py
alithia/utils/supabase_client.py
alithia/utils/zotero_client.py
alithia-0.2.7.dist-info/licenses/LICENSE
alithia-0.2.7.dist-info/METADATA
alithia-0.2.7.dist-info/WHEEL
alithia-0.2.7.dist-info/top_level.txt
alithia-0.2.7.dist-info/RECORD
