Metadata-Version: 2.4
Name: alithia
Version: 0.2.7
Summary: Your ultimate research companion
Author-email: Xiaming Chen <chenxm35@gmail.com>
Maintainer-email: Xiaming Chen <chenxm35@gmail.com>
License-Expression: MIT
Project-URL: Homepage, https://github.com/caesar0301/alithia
Project-URL: Repository, https://github.com/caesar0301/alithia
Project-URL: Issues, https://github.com/caesar0301/alithia/issues
Keywords: research assistant,academic,arxiv,ai agent
Classifier: Development Status :: 3 - Alpha
Classifier: Intended Audience :: Developers
Classifier: Operating System :: OS Independent
Classifier: Programming Language :: Python :: 3
Classifier: Programming Language :: Python :: 3.11
Classifier: Programming Language :: Python :: 3.12
Classifier: Topic :: Scientific/Engineering :: Artificial Intelligence
Requires-Python: >=3.11
License-File: LICENSE
Requires-Dist: cogents-core<2.0.0,>=1.0.0
Requires-Dist: supabase>=2.0.0
Provides-Extra: all
Requires-Dist: alithia[default,paperlens]; extra == "all"
Provides-Extra: default
Requires-Dist: arxiv>=2.1.3; extra == "default"
Requires-Dist: pyzotero>=1.5.25; extra == "default"
Requires-Dist: scikit-learn>=1.5.2; extra == "default"
Requires-Dist: gitignore-parser>=0.1.11; extra == "default"
Requires-Dist: tiktoken>=0.8.0; extra == "default"
Requires-Dist: feedparser>=6.0.11; extra == "default"
Requires-Dist: sentence-transformers>=3.0.0; extra == "default"
Requires-Dist: beautifulsoup4>=4.12.0; extra == "default"
Requires-Dist: lxml>=5.0.0; extra == "default"
Provides-Extra: paperscout
Requires-Dist: alithia[default]; extra == "paperscout"
Provides-Extra: paperlens
Requires-Dist: alithia[docling]; extra == "paperlens"
Provides-Extra: docling
Requires-Dist: docling>=2.58.0; extra == "docling"
Requires-Dist: onnxruntime>=1.23.2; extra == "docling"
Provides-Extra: dev
Requires-Dist: pytest<9,>=8.2; extra == "dev"
Requires-Dist: pytest-cov>=4.0.0; extra == "dev"
Requires-Dist: pytest-asyncio>=1.1.0; extra == "dev"
Requires-Dist: pytest-tornasync>=0.6.0.post2; extra == "dev"
Requires-Dist: pytest-trio>=0.8.0; extra == "dev"
Requires-Dist: pytest-twisted>=1.14.3; extra == "dev"
Requires-Dist: twisted>=25.5.0; extra == "dev"
Requires-Dist: black>=25.1.0; extra == "dev"
Requires-Dist: isort>=6.0.1; extra == "dev"
Requires-Dist: flake8>=7.3.0; extra == "dev"
Requires-Dist: autoflake>=2.3.1; extra == "dev"
Dynamic: license-file
